DocExtractor/__init__.py
DocExtractor/config.py
DocExtractor/input.py
doc_ocr_yakul-0.0.4.dist-info/LICENSE
doc_ocr_yakul-0.0.4.dist-info/METADATA
doc_ocr_yakul-0.0.4.dist-info/WHEEL
doc_ocr_yakul-0.0.4.dist-info/top_level.txt
doc_ocr_yakul-0.0.4.dist-info/RECORD
