Metadata-Version: 2.1
Name: doc-ocr-yakul
Version: 0.0.4
Summary: Text extractor from document
Home-page: UNKNOWN
Author: Crossml
Author-email: yakul@crossml.com
License: MIT
Keywords: easyocr-adaptor,easyocr-extractor,easyocr
Platform: UNKNOWN
Requires-Python: >=3
Requires-Dist: boto3
Requires-Dist: easyocr
Requires-Dist: pdf2image
